setup.py
wallpaste.py
wp.py
wallpaste-0.1.2.dist-info/LICENSE
wallpaste-0.1.2.dist-info/METADATA
wallpaste-0.1.2.dist-info/WHEEL
wallpaste-0.1.2.dist-info/top_level.txt
wallpaste-0.1.2.dist-info/RECORD
