Metadata-Version: 2.1
Name: wallpaste
Version: 0.1.2
Summary: Combine multiple images into one.
Home-page: https://github.com/misobarisic/wallpaste
Author: misobarisic
Author-email: me@misobarisic.com
License: MIT
Platform: UNKNOWN
License-File: LICENSE
Requires-Dist: pillow
